Metadata-Version: 2.1
Name: consolewin
Version: 0.0.9
Summary: A simple package for begginers!
Home-page: UNKNOWN
Author: Adam Yasser
Author-email: adam.y.h.20o1@gmail.com
License: MIT
Keywords: Console
Platform: UNKNOWN
Classifier: Development Status :: 5 - Production/Stable
Classifier: Intended Audience :: Education
Classifier: Operating System :: Microsoft :: Windows :: Windows 10
Classifier: License :: OSI Approved :: MIT License
Classifier: Programming Language :: Python :: 3
License-File: LICENSE.txt
